cvc5_gpl-1.3.2.dist-info/GCC-exception-3.1.txt
cvc5_gpl-1.3.2.dist-info/lgpl-3.0.txt
cvc5_gpl-1.3.2.dist-info/RECORD
cvc5_gpl-1.3.2.dist-info/WHEEL
cvc5_gpl-1.3.2.dist-info/gpl-3.0.txt
cvc5_gpl-1.3.2.dist-info/COPYING
cvc5_gpl-1.3.2.dist-info/minisat-LICENSE
cvc5_gpl-1.3.2.dist-info/top_level.txt
cvc5_gpl-1.3.2.dist-info/METADATA
cvc5_gpl-1.3.2.dist-info/apache-2.0-with-llvm-exceptions.txt
cvc5_gpl-1.3.2.dist-info/pythonic-LICENSE
cvc5/__init__.py
cvc5/cvc5_python_base.pypy39-pp73-darwin.so
cvc5/pythonic/cvc5_pythonic.py
cvc5/pythonic/__init__.py
cvc5/pythonic/cvc5_pythonic_printer.py
cvc5/.dylibs/libcvc5parser.1.dylib
cvc5/.dylibs/libcln.6.dylib
cvc5/.dylibs/libpoly.0.2.0.dylib
cvc5/.dylibs/libpolyxx.0.2.0.dylib
cvc5/.dylibs/libgmp.10.dylib
cvc5/.dylibs/libcvc5.1.dylib
